Metadata-Version: 2.1
Name: DeepCellTL
Version: 0.12.4
Summary: Deep learning for single cell image segmentation
Home-page: https://github.com/vanvalenlab/deepcell-tf
Download-URL: https://github.com/vanvalenlab/deepcell-tf/tarball/0.12.4
Author: The Van Valen Lab
Author-email: vanvalen@caltech.edu
License: LICENSE
Classifier: Intended Audience :: Developers
Classifier: Intended Audience :: Science/Research
Classifier: Operating System :: OS Independent
Classifier: Programming Language :: Python
Classifier: Programming Language :: Python :: 3
Classifier: Programming Language :: Python :: 3.7
Classifier: Programming Language :: Python :: 3.8
Classifier: Programming Language :: Python :: 3.9
Classifier: Topic :: Scientific/Engineering
Classifier: Topic :: Scientific/Engineering :: Artificial Intelligence
Classifier: Topic :: Scientific/Engineering :: Bio-Informatics
Classifier: Topic :: Scientific/Engineering :: Image Processing
Classifier: Topic :: Scientific/Engineering :: Image Recognition
Classifier: Topic :: Software Development :: Libraries
Classifier: Topic :: Software Development :: Libraries :: Python Modules
Requires-Python: >=3.7, <3.11
License-File: LICENSE
Requires-Dist: numpy (>=1.16.6)
Requires-Dist: pydot (<2,>=1.4.2)
Requires-Dist: scipy (<2,>=1.2.3)
Requires-Dist: scikit-image (>=0.14.5)
Requires-Dist: scikit-learn (>=0.20.4)
Requires-Dist: tensorflow (~=2.8.0)
Requires-Dist: spektral (~=1.0.4)
Requires-Dist: jupyter (<2,>=1.0.0)
Requires-Dist: matplotlib
Requires-Dist: opencv-python-headless (<5)
Requires-Dist: deepcell-tracking (~=0.6.1)
Requires-Dist: deepcell-toolbox (~=0.11.2)
Requires-Dist: tensorflow-addons (~=0.17.1) ; platform_machine == "x86_64"
Provides-Extra: tests
Requires-Dist: pytest (<6) ; extra == 'tests'
Requires-Dist: pytest-cov ; extra == 'tests'
Requires-Dist: pytest-pep8 ; extra == 'tests'
